sybil_engine/__init__.py
sybil_engine/app.py
sybil_engine/scenario_loader.py
sybil_engine/config/__init__.py
sybil_engine/config/app_config.py
sybil_engine/contract/__init__.py
sybil_engine/contract/contract.py
sybil_engine/contract/deploy_contract.py
sybil_engine/contract/erc20_test_contract.py
sybil_engine/contract/erc20contract.py
sybil_engine/contract/send.py
sybil_engine/contract/transaction_executor.py
sybil_engine/contract/weth.py
sybil_engine/data/__init__.py
sybil_engine/data/contracts.py
sybil_engine/data/exception.py
sybil_engine/data/networks.py
sybil_engine/data/pairs.py
sybil_engine/data/tokens.py
sybil_engine/domain/__init__.py
sybil_engine/domain/account_storage.py
sybil_engine/domain/dex.py
sybil_engine/domain/swap_facade.py
sybil_engine/domain/balance/__init__.py
sybil_engine/domain/balance/balance.py
sybil_engine/domain/balance/balance_utils.py
sybil_engine/domain/balance/tokens.py
sybil_engine/domain/cex/__init__.py
sybil_engine/domain/cex/binance.py
sybil_engine/domain/cex/cex.py
sybil_engine/domain/cex/okx.py
sybil_engine/module/__init__.py
sybil_engine/module/execution_planner.py
sybil_engine/module/module.py
sybil_engine/module/module_executor.py
sybil_engine/module/modules.py
sybil_engine/resources/abi/erc20.json
sybil_engine/resources/abi/weth.json
sybil_engine/resources/local/contracts.json
sybil_engine/resources/local/networks.json
sybil_engine/resources/local/pairs.json
sybil_engine/resources/local/tokens.json
sybil_engine/utils/__init__.py
sybil_engine/utils/accumulator.py
sybil_engine/utils/app_account_utils.py
sybil_engine/utils/arguments_parser.py
sybil_engine/utils/binance_prices.py
sybil_engine/utils/config_utils.py
sybil_engine/utils/configuration_loader.py
sybil_engine/utils/csv_reader.py
sybil_engine/utils/duplicate_utils.py
sybil_engine/utils/fee_storage.py
sybil_engine/utils/file_loader.py
sybil_engine/utils/gas_utils.py
sybil_engine/utils/google_utils.py
sybil_engine/utils/l0_utils.py
sybil_engine/utils/logs.py
sybil_engine-10.6.3.dist-info/METADATA
sybil_engine-10.6.3.dist-info/WHEEL
sybil_engine-10.6.3.dist-info/top_level.txt
sybil_engine-10.6.3.dist-info/RECORD
