Metadata-Version: 2.4
Name: sybil_engine
Version: 10.6.3
Summary: Engine for web3 smart contracts automatization.
Author-email: Indeoo <indeooars@gmail.com>
License: MIT
Project-URL: Homepage, https://github.com/Indeoo/web3-wizzard-lib/
Requires-Python: >=3.7
Requires-Dist: loguru==0.7.2
Requires-Dist: setuptools==70.0.0
Requires-Dist: ccxt==4.2.100
Requires-Dist: tqdm==4.66.2
Requires-Dist: web3==7.2.0
Requires-Dist: requests==2.32.0
Requires-Dist: pyTelegramBotAPI==4.17.0
Requires-Dist: python-okx==0.2.8
Requires-Dist: termcolor==2.4.0
Requires-Dist: bumpversion==0.6.0
Requires-Dist: binance-connector==3.6.0
Requires-Dist: base58==2.1.1
Requires-Dist: google-api-python-client==2.126.0
Requires-Dist: google-auth-httplib2==0.2.0
Requires-Dist: google-auth-oauthlib==1.2.0
Requires-Dist: eth-tester==0.10.0b4
Requires-Dist: py-evm==0.10.1b2
Requires-Dist: fake-useragent==1.4.0
Requires-Dist: Faker~=27.0.0
Requires-Dist: pk-encryptor==0.0.6
